setup.py
busmon_consumers/__init__.py
busmon_consumers/consumers.py
busmon_consumers.egg-info/PKG-INFO
busmon_consumers.egg-info/SOURCES.txt
busmon_consumers.egg-info/dependency_links.txt
busmon_consumers.egg-info/entry_points.txt
busmon_consumers.egg-info/not-zip-safe
busmon_consumers.egg-info/paster_plugins.txt
busmon_consumers.egg-info/requires.txt
busmon_consumers.egg-info/top_level.txt