Metadata-Version: 1.0
Name: busmon-consumers
Version: 0.4.5
Summary: fedmsg-hub consumers for the busmon webapp
Home-page: http://github.com/ralphbean/busmon
Author: Ralph Bean
Author-email: rbean@redhat.com
License: GPLv2+
Platform: UNKNOWN
